<absadoc annotators=1 senti=>
<absatitle>
  <w>Anonym</w>
  <w>användare</w>
  <w>"</w>
  <w>Q</w>
  <w>"</w>
  <w>/</w>
  <w>pol</w>
  <w>/</w>
  <w>hintar</w>
  <w>om</w>
  <w>massiv</w>
  <w>Deep</w>
  <w>State-upprensning</w>
  <w>i</w>
  <w>USA</w>
  <w>#</w>
  <w>TheStorm</w>
  <w>.</w>
</absatitle>
<absapar id=1>
  <w>Då</w>
  <w>förra</w>
  <w>tråden</w>
  <w>togs</w>
  <w>bort</w>
  <w>så</w>
  <w>kommer</w>
  <w>här</w>
  <w>en</w>
  <absaspan id=1 senti=4>
    <w>bättre</w>
  </absaspan>
  <absaspan id=2>
    <w>version</w>
  </absaspan>
  <w>med</w>
  <w>de</w>
  <absaspan id=3 senti=4>
    <w>intressantaste</w>
  </absaspan>
  <absaspan id=4>
    <w>bitarna</w>
  </absaspan>
  <w>.</w>
</absapar>
<absapar id=2>
  <w>En</w>
  <w>anonym</w>
  <w>användare</w>
  <w>som</w>
  <w>signerar</w>
  <w>sina</w>
  <w>inlägg</w>
  <w>med</w>
  <absaspan id=5>
    <w>"</w>
    <w>Q</w>
    <w>"</w>
  </absaspan>
  <w>har</w>
  <w>senaste</w>
  <w>dagarna</w>
  <w>postat</w>
  <w>en</w>
  <w>hel</w>
  <w>del</w>
  <absaspan id=6 senti=4>
    <w>intressanta</w>
  </absaspan>
  <absaspan id=7>
    <w>inlägg</w>
  </absaspan>
  <w>på</w>
  <w>4Chans</w>
  <w>/</w>
  <w>pol</w>
  <w>/</w>
  <w>.</w>
  <w>Enligt</w>
  <w>han</w>
  <w>själv</w>
  <w>är</w>
  <w>han</w>
  <w>en</w>
  <w>"</w>
  <w>Q-Clearence</w>
  <w>patriot</w>
  <w>"</w>
  <w>,</w>
  <w>vilket</w>
  <w>skulle</w>
  <w>ge</w>
  <w>honom</w>
  <w>access</w>
  <w>till</w>
  <w>väldigt</w>
  <w>känslig</w>
  <w>information</w>
  <w>.</w>
</absapar>
<absapar id=3>
  <w>Hans</w>
  <w>inlägg</w>
  <w>är</w>
  <w>i</w>
  <w>stort</w>
  <w>sett</w>
  <w>bara</w>
  <w>frågor</w>
  <w>som</w>
  <w>användarna</w>
  <w>själva</w>
  <w>får</w>
  <w>leta</w>
  <w>fram</w>
  <w>svaret</w>
  <w>på</w>
  <w>,</w>
  <w>men</w>
  <w>påstår</w>
  <w>att</w>
  <w>det</w>
  <w>inom</w>
  <w>kort</w>
  <w>ska</w>
  <w>ske</w>
  <w>en</w>
  <w>massiv</w>
  <w>uppresnings</w>
  <w>i</w>
  <absaspan id=8 senti=1>
    <w>de</w>
    <w>korruptas</w>
    <w>högborg</w>
  </absaspan>
  <absaspan id=9>
    <w>Washington</w>
    <w>DC</w>
  </absaspan>
  <w>.</w>
  <w>Ryktas</w>
  <w>om</w>
  <w>att</w>
  <w>Podestas</w>
  <w>,</w>
  <w>Hillary</w>
  <w>Clinton</w>
  <w>,</w>
  <w>Soros</w>
  <w>,</w>
  <w>McCain</w>
  <w>m.m</w>
  <w>snart</w>
  <w>ryker</w>
  <w>.</w>
  <w>En</w>
  <w>skandal</w>
  <w>som</w>
  <w>skulle</w>
  <w>få</w>
  <w>alla</w>
  <w>andra</w>
  <w>skandaler</w>
  <w>i</w>
  <w>världshistorien</w>
  <w>att</w>
  <w>blekna</w>
  <w>.</w>
  <w>Topskiktet</w>
  <w>av</w>
  <w>eliten</w>
  <w>är</w>
  <w>påväg</w>
  <w>ner</w>
  <w>.</w>
</absapar>
<absapar id=4>
  <w>För</w>
  <w>närvarande</w>
  <w>är</w>
  <w>det</w>
  <w>33</w>
  <w>"</w>
  <w>sealed</w>
  <w>indictments</w>
  <w>"</w>
  <w>ute</w>
  <w>i</w>
  <w>Washington</w>
  <w>DC</w>
  <w>,</w>
  <w>åtal</w>
  <w>som</w>
  <w>ännu</w>
  <w>är</w>
  <w>dolda</w>
  <w>för</w>
  <w>allmänheten</w>
  <w>och</w>
  <w>där</w>
  <absaspan id=10>
    <w>man</w>
  </absaspan>
  <absaspan id=11 senti=2>
    <w>inte</w>
    <w>vill</w>
  </absaspan>
  <absaspan id=12>
    <w>att</w>
    <w>den</w>
    <w>åtalade</w>
    <w>ska</w>
    <w>bli</w>
    <w>"</w>
    <w>tipped</w>
    <w>off</w>
    <w>"</w>
    <w>i</w>
    <w>förväg</w>
  </absaspan>
  <w>.</w>
</absapar>
<absapar id=5>
  <w>.</w>
  <w>+</w>
  <w>50</w>
  <w>i</w>
  <w>angränsade</w>
  <w>Virginia</w>
  <w>:</w>
  <w>.</w>
</absapar>
<absapar id=6>
  <w>Några</w>
  <w>av</w>
  <w>"</w>
  <w>Q"s</w>
  <w>posts</w>
  <w>:</w>
  <w>.</w>
</absapar>
<absapar id=7>
  <w>Alla</w>
  <w>"</w>
  <w>Q"s</w>
  <w>posts</w>
  <w>går</w>
  <w>att</w>
  <w>finna</w>
  <w>här</w>
  <w>:</w>
  <w>.</w>
</absapar>
<absapar id=8>
  <w>Användare</w>
  <w>har</w>
  <w>försökt</w>
  <w>komma</w>
  <w>med</w>
  <w>svar</w>
  <w>på</w>
  <w>hans</w>
  <w>frågor</w>
  <w>här</w>
  <w>:</w>
  <w>.</w>
</absapar>
<absapar id=9>
  <w>Exempel</w>
  <w>:</w>
  <w>.</w>
</absapar>
<absapar id=10>
  <w>I</w>
  <w>trådarna</w>
  <w>skriver</w>
  <w>folk</w>
  <w>(</w>
  <w>som</w>
  <w>påstår</w>
  <w>sig</w>
  <w>vara</w>
  <w>aktiva</w>
  <w>)</w>
  <w>inom</w>
  <w>militären</w>
  <w>att</w>
  <w>det</w>
  <w>sker</w>
  <w>en</w>
  <w>hel</w>
  <w>del</w>
  <w>rörelser</w>
  <w>.</w>
  <w>Någonting</w>
  <w>är</w>
  <w>på</w>
  <w>gång</w>
  <w>.</w>
</absapar>
<absapar id=11>
  <w>Q</w>
  <w>frågar</w>
  <w>:</w>
  <w>.</w>
</absapar>
<absapar id=12>
  <w>Trump</w>
  <w>har</w>
  <w>speciell</w>
  <w>makt</w>
  <w>över</w>
  <w>marinen</w>
  <w>och</w>
  <w>kan</w>
  <w>använda</w>
  <w>dem</w>
  <w>mot</w>
  <absaspan id=13 senti=1>
    <w>AFA-kaosare</w>
    <w>och</w>
    <w>annat</w>
    <w>löst</w>
    <w>folk</w>
  </absaspan>
  <w>som</w>
  <w>kan</w>
  <w>tänkas</w>
  <w>göra</w>
  <w>uppror</w>
  <w>när</w>
  <w>Clinton</w>
  <w>,</w>
  <w>Podestas</w>
  <w>,</w>
  <w>Soros</w>
  <w>mfl</w>
  <w>blir</w>
  <w>plockade</w>
  <absaspan id=14>
    <w>.</w>
  </absaspan>
  <w>Om</w>
  <w>allt</w>
  <w>detta</w>
  <w>stämmer</w>
  <w>så</w>
  <absaspan id=15>
    <w>skulle</w>
    <w>Mainstream</w>
    <w>media</w>
    <w>direkt</w>
    <w>gå</w>
    <w>ut</w>
    <w>med</w>
  </absaspan>
  <w>.</w>
</absapar>
<absapar id=13>
  <w>vilket</w>
  <absaspan id=16 senti=1>
    <w>hade</w>
    <w>ställt</w>
    <w>till</w>
    <w>med</w>
    <w>en</w>
    <w>jävla</w>
    <w>massa</w>
    <w>oreda</w>
  </absaspan>
  <absaspan id=17>
    <w>.</w>
  </absaspan>
</absapar>
<absapar id=14>
  <w>Inte</w>
  <w>bara</w>
  <w>demokrater</w>
  <w>som</w>
  <w>ligger</w>
  <w>i</w>
  <w>siktet</w>
  <w>:</w>
  <w>.</w>
</absapar>
<absapar id=15>
  <w>Detta</w>
  <w>är</w>
  <w>också</w>
  <w>intressant</w>
  <w>:</w>
  <w>.</w>
</absapar>
<absapar id=16>
  <w>Tänkte</w>
  <w>att</w>
  <w>vi</w>
  <w>i</w>
  <w>denna</w>
  <w>tråd</w>
  <w>diskuterar</w>
  <w>den</w>
  <w>omryktade</w>
  <w>#</w>
  <w>TheStorm</w>
  <w>som</w>
  <w>nu</w>
  <w>sägs</w>
  <w>vara</w>
  <w>i</w>
  <w>rullning</w>
  <w>,</w>
  <w>med</w>
  <w>kommande</w>
  <w>gripanden</w>
  <w>av</w>
  <w>väldigt</w>
  <w>högt</w>
  <w>uppsatta</w>
  <w>personer</w>
  <w>i</w>
  <w>USA</w>
  <w>.</w>
  <w>Vi</w>
  <w>snackar</w>
  <w>Nûrnberg-rättegångarna</w>
  <w>i</w>
  <w>kvadrat</w>
  <w>.</w>
  <absaspan id=18 senti=1>
    <w>Korruption</w>
  </absaspan>
  <w>som</w>
  <w>rör</w>
  <w>allt</w>
  <w>från</w>
  <absaspan id=19 senti=1>
    <w>pengatvätt</w>
    <w>,</w>
    <w>vapenhandel</w>
    <w>,</w>
    <w>trafficking</w>
    <w>,</w>
    <w>barnprostitution</w>
    <w>m.m</w>
  </absaspan>
  <absaspan id=20 senti=1>
    <w>.</w>
  </absaspan>
</absapar>
<absapar id=17>
  <w>Allt</w>
  <w>som</w>
  <w>rör</w>
  <w>"</w>
  <w>Q"s</w>
  <w>posts</w>
  <w>anser</w>
  <w>jag</w>
  <w>också</w>
  <w>vara</w>
  <w>relevant</w>
  <w>för</w>
  <w>tråden</w>
  <w>!</w>
  <w>.</w>
</absapar>
</absadoc>
